bedrock/__init__.py
bedrock/blueprint.py
bedrock/manifest.py
brock-1.0.2.dist-info/LICENSE
brock-1.0.2.dist-info/METADATA
brock-1.0.2.dist-info/WHEEL
brock-1.0.2.dist-info/entry_points.txt
brock-1.0.2.dist-info/top_level.txt
brock-1.0.2.dist-info/RECORD
