Metadata-Version: 2.1
Name: brock
Version: 1.0.2
Summary: A collection of Terraform-based blueprints
Home-page: https://github.com/micronode/bedrock
Author: Ben Fortuna
Author-email: fortuna@micronode.com
License: UNKNOWN
Platform: UNKNOWN
Requires-Python: >=3.7
Requires-Dist: PyYAML (>=5.1)
Requires-Dist: docker (>=3.7.2)
